auto_crud/__init__.py
auto_crud/core/__init__.py
auto_crud/core/crud/__init__.py
auto_crud/core/crud/base.py
auto_crud/core/crud/decorators.py
auto_crud/core/crud/filter.py
auto_crud/core/crud/router.py
auto_crud/core/crud/types.py
auto_crud/core/errors/__init__.py
auto_crud/core/schemas/__init__.py
auto_crud/core/schemas/pagination.py
auto_crud/dependencies/page_param.py
fastapi_autocrud-0.1.5.dist-info/METADATA
fastapi_autocrud-0.1.5.dist-info/WHEEL
fastapi_autocrud-0.1.5.dist-info/RECORD
