Metadata-Version: 2.4
Name: FastAPI-AutoCRUD
Version: 0.1.5
Summary: A powerful, enterprise-level FastAPI CRUD router factory that automatically generates REST endpoints with advanced features like filtering, pagination, searching, sorting, bulk operations, and custom endpoint decorators.
Author-email: FastAPI-AutoCRUD Contributors <support@autocrud.dev>
License: MIT
Keywords: api,crud,fastapi,pydantic,rest,router,sqlalchemy
Classifier: Development Status :: 4 - Beta
Classifier: Framework :: FastAPI
Classifier: Intended Audience :: Developers
Classifier: License :: OSI Approved :: MIT License
Classifier: Operating System :: OS Independent
Classifier: Programming Language :: Python :: 3
Classifier: Programming Language :: Python :: 3.12
Classifier: Programming Language :: Python :: 3.13
Classifier: Topic :: Internet :: WWW/HTTP :: HTTP Servers
Classifier: Topic :: Software Development :: Libraries :: Application Frameworks
Classifier: Topic :: Software Development :: Libraries :: Python Modules
Requires-Python: >=3.12
Requires-Dist: fastapi[standard]>=0.115.14
Requires-Dist: loguru>=0.7.3
Requires-Dist: pydantic>=2.11.7
Requires-Dist: sqlalchemy[asyncio]>=2.0.41
Requires-Dist: tenacity>=9.1.2
Provides-Extra: test
Requires-Dist: aiosqlite>=0.19.0; extra == 'test'
Requires-Dist: httpx>=0.25.0; extra == 'test'
Requires-Dist: pytest-asyncio>=0.21.0; extra == 'test'
Requires-Dist: pytest-cov>=4.1.0; extra == 'test'
Requires-Dist: pytest>=7.4.0; extra == 'test'
